LICENSE
MANIFEST.in
README.md
setup.py
client/__init__.py
client/__main__.py
client/config.ok
client/exceptions.py
client/api/__init__.py
client/api/assignment.py
client/api/notebook.py
client/cli/__init__.py
client/cli/lock.py
client/cli/ok.py
client/cli/publish.py
client/cli/test.py
client/cli/common/__init__.py
client/cli/common/messages.py
client/protocols/__init__.py
client/protocols/analytics.py
client/protocols/autostyle.py
client/protocols/backup.py
client/protocols/collaborate.py
client/protocols/file_contents.py
client/protocols/grading.py
client/protocols/hinting.py
client/protocols/lock.py
client/protocols/rate_limit.py
client/protocols/scoring.py
client/protocols/testing.py
client/protocols/trace.py
client/protocols/unlock.py
client/protocols/common/__init__.py
client/protocols/common/models.py
client/sources/__init__.py
client/sources/common/__init__.py
client/sources/common/core.py
client/sources/common/importing.py
client/sources/common/interpreter.py
client/sources/common/models.py
client/sources/common/pyconsole.py
client/sources/doctest/__init__.py
client/sources/doctest/models.py
client/sources/ok_test/__init__.py
client/sources/ok_test/concept.py
client/sources/ok_test/doctest.py
client/sources/ok_test/logic.py
client/sources/ok_test/models.py
client/sources/ok_test/scheme.py
client/sources/ok_test/sqlite.py
client/sources/ok_test/wwpp.py
client/sources/scheme_test/__init__.py
client/sources/scheme_test/models.py
client/utils/__init__.py
client/utils/assess_id_util.py
client/utils/auth.py
client/utils/config.py
client/utils/debug.py
client/utils/format.py
client/utils/guidance.py
client/utils/locking.py
client/utils/network.py
client/utils/output.py
client/utils/prompt.py
client/utils/software_update.py
client/utils/storage.py
client/utils/timer.py
client/utils/firebase/__init__.py
client/utils/firebase/pyrebase.py
client/utils/firebase/sseclient.py
test_9112736.egg-info/PKG-INFO
test_9112736.egg-info/SOURCES.txt
test_9112736.egg-info/dependency_links.txt
test_9112736.egg-info/entry_points.txt
test_9112736.egg-info/requires.txt
test_9112736.egg-info/top_level.txt