Metadata-Version: 1.1
Name: test-9112736
Version: 1.15.44
Summary: ok.py supports programming projects by running tests, tracking progress, and assisting in debugging.
Home-page: https://github.com/nnbaokhang/ok-client
Author: John Denero, Soumya Basu, Stephen Martinis, Sharad Vikram, Albert Wu
Author-email: UNKNOWN
License: Apache License, Version 2.0
Keywords: education,autograding
Platform: UNKNOWN
Classifier: Programming Language :: Python :: 3.4
Classifier: Programming Language :: Python :: 3.5
Classifier: Programming Language :: Python :: 3.6
